redisaq/__init__.py
redisaq/common.py
redisaq/constants.py
redisaq/consumer.py
redisaq/errors.py
redisaq/keys.py
redisaq/models.py
redisaq/producer.py
redisaq/types.py
redisaq/utils.py
redisaq-0.1.4.dist-info/LICENSE
redisaq-0.1.4.dist-info/METADATA
redisaq-0.1.4.dist-info/WHEEL
redisaq-0.1.4.dist-info/RECORD
