Metadata-Version: 2.1
Name: redisaq
Version: 0.1.4
Summary: A lightweight, async Redis-based queue for small applications, alternative to Kafka.
Home-page: https://github.com/vuongtlt13/redisaq
License: MIT
Author: Do Quoc Vuong
Author-email: vuongtlt13@gmail.com
Requires-Python: >=3.8,<4.0
Classifier: License :: OSI Approved :: MIT License
Classifier: Programming Language :: Python :: 3
Classifier: Programming Language :: Python :: 3.8
Classifier: Programming Language :: Python :: 3.9
Classifier: Programming Language :: Python :: 3.10
Classifier: Programming Language :: Python :: 3.11
Classifier: Programming Language :: Python :: 3.12
Classifier: Programming Language :: Python :: 3.13
Requires-Dist: orjson (>=3.10.15,<4.0.0)
Requires-Dist: prometheus-client (>=0.20.0,<0.21.0)
Requires-Dist: redis (>=5.2.1,<6.0.0)
Project-URL: Documentation, https://redisaq.readthedocs.io
Project-URL: Repository, https://github.com/vuongtlt13/redisaq
